whatsobservable.py
WhatsObservable-0.1.2.dist-info/DESCRIPTION.rst
WhatsObservable-0.1.2.dist-info/METADATA
WhatsObservable-0.1.2.dist-info/RECORD
WhatsObservable-0.1.2.dist-info/WHEEL
WhatsObservable-0.1.2.dist-info/metadata.json
WhatsObservable-0.1.2.dist-info/top_level.txt
