Metadata-Version: 2.0
Name: WhatsObservable
Version: 0.1.2
Summary: Determine which small solar system bodies are observable from a given location at a given time
Home-page: http://github.com/henryroe/WhatsObservable
Author: Henry Roe
Author-email: hroe@hroe.me
License: LICENSE.txt
Platform: UNKNOWN
Requires-Dist: pandas (>=0.10.1)
Requires-Dist: pyephem (>=3.7.5.1)
